pyseed/Benchmark_functions.py
pyseed/Test_pySEED.py
pyseed/__init__.py
pyseed/pySEED.py
pySEED-2.0.0.dist-info/LICENSE
pySEED-2.0.0.dist-info/METADATA
pySEED-2.0.0.dist-info/WHEEL
pySEED-2.0.0.dist-info/top_level.txt
pySEED-2.0.0.dist-info/RECORD
