Metadata-Version: 2.1
Name: pySEED
Version: 2.0.0
Summary: pySEED is a python inplementation of symmetric-approximation energy-based estimation of distribution (seed): a continuous optimization algorithm, that was published in IEEE Accsses, with DOI: 10.1109/ACCESS.2019.2948199
Home-page: https://github.com/LIDT-Lab/pySEED.git
Author: Valentin Calzada Ledesma, Juan de Anda Suarez
Author-email: juan.ds@purisima.tecnm.mx
License: UNKNOWN
Platform: UNKNOWN
Classifier: Programming Language :: Python :: 3
Classifier: License :: OSI Approved :: MIT License
Classifier: Operating System :: OS Independent
Requires-Python: >=3.5.2
Requires-Dist: numpy (>=1.18.2)
